<?xml version="1.0" encoding="windows-1252" ?>
<!DOCTYPE ViewObject SYSTEM "jbo_03_01.dtd">
<!---->
<ViewObject
  xmlns="http://xmlns.oracle.com/bc4j"
  Name="ParkingSpaceInventoryRoView"
  Version="11.1.1.59.23"
  BindingStyle="OracleName"
  CustomQuery="true"
  PageIterMode="Full"
  UseGlueCode="false"
  RowClass="vo.ParkingSpaceInventoryRoViewRowImpl"
  ComponentClass="vo.ParkingSpaceInventoryRoViewImpl"
  RowInterface="vo.common.ParkingSpaceInventoryRoViewRow"
  ClientRowProxyName="vo.client.ParkingSpaceInventoryRoViewRowClient">
  <DesignTime>
    <Attr Name="_codeGenFlag2" Value="Access|Coll|VarAccess"/>
    <Attr Name="_isExpertMode" Value="true"/>
    <Attr Name="_isCodegen" Value="true"/>
  </DesignTime>
  <SQLQuery>
    <![CDATA[SELECT ParkingSpaceInventory.PARKING_SPACE_ID,
       ParkingSpaceInventory.POST_ID,
       ParkingSpaceInventory.MS_PAY_STATION_ID,
       ParkingSpaceInventory.MS_SPACE_NUM,
       ParkingSpaceInventory.SENSOR_FLAG,
       ParkingSpaceInventory.ON_OFFSTREET_TYPE,
       ParkingSpaceInventory.OSP_ID,
       ParkingSpaceInventory.JURISDICTION,
       ParkingSpaceInventory.PM_DISTRICT_ID,
       ParkingSpaceInventory.BLOCKFACE_ID,
       ParkingSpaceInventory.ACTIVE_METER_FLAG,
       ParkingSpaceInventory.REASON_CODE,
       ParkingSpaceInventory.SMART_METER_FLAG,
       ParkingSpaceInventory.METER_TYPE,
       ParkingSpaceInventory.METER_VENDOR,
       ParkingSpaceInventory.METER_MODEL,
       ParkingSpaceInventory.CAP_COLOR,
       ParkingSpaceInventory.PCO_BEAT,
       ParkingSpaceInventory.OLD_RATE_AREA,
       ParkingSpaceInventory.STREET_ID,
       ParkingSpaceInventory.STREET_NAME,
       ParkingSpaceInventory.STREET_NUM,
       ParkingSpaceInventory.PARITY_DIGIT_POSITION,
       ParkingSpaceInventory.STREET_SEG_CTRLN_ID,
       ParkingSpaceInventory.ORIENTATION,
       ParkingSpaceInventory.LONGITUDE,
       ParkingSpaceInventory.LATITUDE,
       ParkingSpaceInventory.GEOM,
       ParkingSpaceInventory.LEGISLATION_REF,
       ParkingSpaceInventory.LEGISLATION_DT,
       ParkingSpaceInventory.WORK_ORDER,
       ParkingSpaceInventory.COMMENTS,
       ParkingSpaceInventory.CREATED_DT,
       ParkingSpaceInventory.LAST_UPD_DT,
       ParkingSpaceInventory.LAST_UPD_USER,
       ParkingSpaceInventory.LAST_UPD_PGM
FROM PARKING_SPACE_INVENTORY ParkingSpaceInventory]]>
  </SQLQuery>
  <ViewAttribute
    Name="ParkingSpaceId"
    IsUpdateable="false"
    IsPersistent="false"
    IsNotNull="true"
    PrecisionRule="true"
    Type="oracle.jbo.domain.Number"
    ColumnType="NUMBER"
    AliasName="PARKING_SPACE_ID"
    Expression="PARKING_SPACE_ID"
    SQLType="NUMERIC">
    <DesignTime>
      <Attr Name="_DisplaySize" Value="22"/>
    </DesignTime>
  </ViewAttribute>
  <ViewAttribute
    Name="PostId"
    IsUpdateable="false"
    IsPersistent="false"
    IsNotNull="true"
    PrecisionRule="true"
    Precision="9"
    Type="java.lang.String"
    ColumnType="VARCHAR2"
    AliasName="POST_ID"
    Expression="POST_ID"
    SQLType="VARCHAR">
    <DesignTime>
      <Attr Name="_DisplaySize" Value="9"/>
    </DesignTime>
  </ViewAttribute>
  <ViewAttribute
    Name="MsPayStationId"
    IsUpdateable="false"
    IsPersistent="false"
    PrecisionRule="true"
    Precision="9"
    Type="java.lang.String"
    ColumnType="VARCHAR2"
    AliasName="MS_PAY_STATION_ID"
    Expression="MS_PAY_STATION_ID"
    SQLType="VARCHAR">
    <DesignTime>
      <Attr Name="_DisplaySize" Value="9"/>
    </DesignTime>
  </ViewAttribute>
  <ViewAttribute
    Name="MsSpaceNum"
    IsUpdateable="false"
    IsPersistent="false"
    PrecisionRule="true"
    Type="oracle.jbo.domain.Number"
    ColumnType="NUMBER"
    AliasName="MS_SPACE_NUM"
    Expression="MS_SPACE_NUM"
    SQLType="NUMERIC">
    <DesignTime>
      <Attr Name="_DisplaySize" Value="22"/>
    </DesignTime>
  </ViewAttribute>
  <ViewAttribute
    Name="SensorFlag"
    IsUpdateable="false"
    IsPersistent="false"
    PrecisionRule="true"
    Precision="1"
    Type="java.lang.String"
    ColumnType="CHAR"
    AliasName="SENSOR_FLAG"
    Expression="SENSOR_FLAG"
    SQLType="VARCHAR">
    <DesignTime>
      <Attr Name="_DisplaySize" Value="1"/>
    </DesignTime>
  </ViewAttribute>
  <ViewAttribute
    Name="OnOffstreetType"
    IsUpdateable="false"
    IsPersistent="false"
    PrecisionRule="true"
    Precision="3"
    Type="java.lang.String"
    ColumnType="VARCHAR2"
    AliasName="ON_OFFSTREET_TYPE"
    Expression="ON_OFFSTREET_TYPE"
    SQLType="VARCHAR">
    <DesignTime>
      <Attr Name="_DisplaySize" Value="3"/>
    </DesignTime>
  </ViewAttribute>
  <ViewAttribute
    Name="OspId"
    IsUpdateable="false"
    IsPersistent="false"
    PrecisionRule="true"
    Type="oracle.jbo.domain.Number"
    ColumnType="NUMBER"
    AliasName="OSP_ID"
    Expression="OSP_ID"
    SQLType="NUMERIC">
    <DesignTime>
      <Attr Name="_DisplaySize" Value="22"/>
    </DesignTime>
  </ViewAttribute>
  <ViewAttribute
    Name="Jurisdiction"
    IsUpdateable="false"
    IsPersistent="false"
    PrecisionRule="true"
    Precision="5"
    Type="java.lang.String"
    ColumnType="VARCHAR2"
    AliasName="JURISDICTION"
    Expression="JURISDICTION"
    SQLType="VARCHAR">
    <DesignTime>
      <Attr Name="_DisplaySize" Value="5"/>
    </DesignTime>
  </ViewAttribute>
  <ViewAttribute
    Name="PmDistrictId"
    IsUpdateable="false"
    IsPersistent="false"
    PrecisionRule="true"
    Type="oracle.jbo.domain.Number"
    ColumnType="NUMBER"
    AliasName="PM_DISTRICT_ID"
    Expression="PM_DISTRICT_ID"
    SQLType="NUMERIC">
    <DesignTime>
      <Attr Name="_DisplaySize" Value="22"/>
    </DesignTime>
  </ViewAttribute>
  <ViewAttribute
    Name="BlockfaceId"
    IsUpdateable="false"
    IsPersistent="false"
    PrecisionRule="true"
    Type="oracle.jbo.domain.Number"
    ColumnType="NUMBER"
    AliasName="BLOCKFACE_ID"
    Expression="BLOCKFACE_ID"
    SQLType="NUMERIC">
    <DesignTime>
      <Attr Name="_DisplaySize" Value="22"/>
    </DesignTime>
  </ViewAttribute>
  <ViewAttribute
    Name="ActiveMeterFlag"
    IsUpdateable="false"
    IsPersistent="false"
    PrecisionRule="true"
    Precision="1"
    Type="java.lang.String"
    ColumnType="CHAR"
    AliasName="ACTIVE_METER_FLAG"
    Expression="ACTIVE_METER_FLAG"
    SQLType="VARCHAR">
    <DesignTime>
      <Attr Name="_DisplaySize" Value="1"/>
    </DesignTime>
  </ViewAttribute>
  <ViewAttribute
    Name="ReasonCode"
    IsUpdateable="false"
    IsPersistent="false"
    PrecisionRule="true"
    Precision="2"
    Type="java.lang.String"
    ColumnType="VARCHAR2"
    AliasName="REASON_CODE"
    Expression="REASON_CODE"
    SQLType="VARCHAR">
    <DesignTime>
      <Attr Name="_DisplaySize" Value="2"/>
    </DesignTime>
  </ViewAttribute>
  <ViewAttribute
    Name="SmartMeterFlag"
    IsUpdateable="false"
    IsPersistent="false"
    PrecisionRule="true"
    Precision="1"
    Type="java.lang.String"
    ColumnType="CHAR"
    AliasName="SMART_METER_FLAG"
    Expression="SMART_METER_FLAG"
    SQLType="VARCHAR">
    <DesignTime>
      <Attr Name="_DisplaySize" Value="1"/>
    </DesignTime>
  </ViewAttribute>
  <ViewAttribute
    Name="MeterType"
    IsUpdateable="false"
    IsPersistent="false"
    PrecisionRule="true"
    Precision="2"
    Type="java.lang.String"
    ColumnType="VARCHAR2"
    AliasName="METER_TYPE"
    Expression="METER_TYPE"
    SQLType="VARCHAR">
    <DesignTime>
      <Attr Name="_DisplaySize" Value="2"/>
    </DesignTime>
  </ViewAttribute>
  <ViewAttribute
    Name="MeterVendor"
    IsUpdateable="false"
    IsPersistent="false"
    PrecisionRule="true"
    Precision="10"
    Type="java.lang.String"
    ColumnType="VARCHAR2"
    AliasName="METER_VENDOR"
    Expression="METER_VENDOR"
    SQLType="VARCHAR">
    <DesignTime>
      <Attr Name="_DisplaySize" Value="10"/>
    </DesignTime>
  </ViewAttribute>
  <ViewAttribute
    Name="MeterModel"
    IsUpdateable="false"
    IsPersistent="false"
    PrecisionRule="true"
    Precision="10"
    Type="java.lang.String"
    ColumnType="VARCHAR2"
    AliasName="METER_MODEL"
    Expression="METER_MODEL"
    SQLType="VARCHAR">
    <DesignTime>
      <Attr Name="_DisplaySize" Value="10"/>
    </DesignTime>
  </ViewAttribute>
  <ViewAttribute
    Name="CapColor"
    IsUpdateable="false"
    IsPersistent="false"
    PrecisionRule="true"
    Precision="10"
    Type="java.lang.String"
    ColumnType="VARCHAR2"
    AliasName="CAP_COLOR"
    Expression="CAP_COLOR"
    SQLType="VARCHAR">
    <DesignTime>
      <Attr Name="_DisplaySize" Value="10"/>
    </DesignTime>
  </ViewAttribute>
  <ViewAttribute
    Name="PcoBeat"
    IsUpdateable="false"
    IsPersistent="false"
    PrecisionRule="true"
    Precision="7"
    Type="java.lang.String"
    ColumnType="VARCHAR2"
    AliasName="PCO_BEAT"
    Expression="PCO_BEAT"
    SQLType="VARCHAR">
    <DesignTime>
      <Attr Name="_DisplaySize" Value="7"/>
    </DesignTime>
  </ViewAttribute>
  <ViewAttribute
    Name="OldRateArea"
    IsUpdateable="false"
    IsPersistent="false"
    PrecisionRule="true"
    Precision="10"
    Type="java.lang.String"
    ColumnType="VARCHAR2"
    AliasName="OLD_RATE_AREA"
    Expression="OLD_RATE_AREA"
    SQLType="VARCHAR">
    <DesignTime>
      <Attr Name="_DisplaySize" Value="10"/>
    </DesignTime>
  </ViewAttribute>
  <ViewAttribute
    Name="StreetId"
    IsUpdateable="false"
    IsPersistent="false"
    PrecisionRule="true"
    Type="oracle.jbo.domain.Number"
    ColumnType="NUMBER"
    AliasName="STREET_ID"
    Expression="STREET_ID"
    SQLType="NUMERIC">
    <DesignTime>
      <Attr Name="_DisplaySize" Value="22"/>
    </DesignTime>
  </ViewAttribute>
  <ViewAttribute
    Name="StreetName"
    IsUpdateable="false"
    IsPersistent="false"
    PrecisionRule="true"
    Precision="30"
    Type="java.lang.String"
    ColumnType="VARCHAR2"
    AliasName="STREET_NAME"
    Expression="STREET_NAME"
    SQLType="VARCHAR">
    <DesignTime>
      <Attr Name="_DisplaySize" Value="30"/>
    </DesignTime>
  </ViewAttribute>
  <ViewAttribute
    Name="StreetNum"
    IsUpdateable="false"
    IsPersistent="false"
    PrecisionRule="true"
    Type="oracle.jbo.domain.Number"
    ColumnType="NUMBER"
    AliasName="STREET_NUM"
    Expression="STREET_NUM"
    SQLType="NUMERIC">
    <DesignTime>
      <Attr Name="_DisplaySize" Value="22"/>
    </DesignTime>
  </ViewAttribute>
  <ViewAttribute
    Name="ParityDigitPosition"
    IsUpdateable="false"
    IsPersistent="false"
    PrecisionRule="true"
    Precision="1"
    Type="java.lang.String"
    ColumnType="CHAR"
    AliasName="PARITY_DIGIT_POSITION"
    Expression="PARITY_DIGIT_POSITION"
    SQLType="VARCHAR">
    <DesignTime>
      <Attr Name="_DisplaySize" Value="1"/>
    </DesignTime>
  </ViewAttribute>
  <ViewAttribute
    Name="StreetSegCtrlnId"
    IsUpdateable="false"
    IsPersistent="false"
    PrecisionRule="true"
    Type="oracle.jbo.domain.Number"
    ColumnType="NUMBER"
    AliasName="STREET_SEG_CTRLN_ID"
    Expression="STREET_SEG_CTRLN_ID"
    SQLType="NUMERIC">
    <DesignTime>
      <Attr Name="_DisplaySize" Value="22"/>
    </DesignTime>
  </ViewAttribute>
  <ViewAttribute
    Name="Orientation"
    IsUpdateable="false"
    IsPersistent="false"
    PrecisionRule="true"
    Type="oracle.jbo.domain.Number"
    ColumnType="NUMBER"
    AliasName="ORIENTATION"
    Expression="ORIENTATION"
    SQLType="NUMERIC">
    <DesignTime>
      <Attr Name="_DisplaySize" Value="22"/>
    </DesignTime>
  </ViewAttribute>
  <ViewAttribute
    Name="Longitude"
    IsUpdateable="false"
    IsPersistent="false"
    PrecisionRule="true"
    Type="oracle.jbo.domain.Number"
    ColumnType="NUMBER"
    AliasName="LONGITUDE"
    Expression="LONGITUDE"
    SQLType="NUMERIC">
    <DesignTime>
      <Attr Name="_DisplaySize" Value="22"/>
    </DesignTime>
  </ViewAttribute>
  <ViewAttribute
    Name="Latitude"
    IsUpdateable="false"
    IsPersistent="false"
    PrecisionRule="true"
    Type="oracle.jbo.domain.Number"
    ColumnType="NUMBER"
    AliasName="LATITUDE"
    Expression="LATITUDE"
    SQLType="NUMERIC">
    <DesignTime>
      <Attr Name="_DisplaySize" Value="22"/>
    </DesignTime>
  </ViewAttribute>
  <ViewAttribute
    Name="Geom"
    IsUpdateable="false"
    IsQueriable="false"
    IsPersistent="false"
    PrecisionRule="true"
    Type="java.lang.Object"
    ColumnType="MDSYS.SDO_GEOMETRY"
    AliasName="GEOM"
    Expression="GEOM"
    SQLType="STRUCT"/>
  <ViewAttribute
    Name="LegislationRef"
    IsUpdateable="false"
    IsPersistent="false"
    PrecisionRule="true"
    Precision="10"
    Type="java.lang.String"
    ColumnType="VARCHAR2"
    AliasName="LEGISLATION_REF"
    Expression="LEGISLATION_REF"
    SQLType="VARCHAR">
    <DesignTime>
      <Attr Name="_DisplaySize" Value="10"/>
    </DesignTime>
  </ViewAttribute>
  <ViewAttribute
    Name="LegislationDt"
    IsUpdateable="false"
    IsPersistent="false"
    PrecisionRule="true"
    Type="oracle.jbo.domain.Date"
    ColumnType="DATE"
    AliasName="LEGISLATION_DT"
    Expression="LEGISLATION_DT"
    SQLType="DATE">
    <DesignTime>
      <Attr Name="_DisplaySize" Value="7"/>
    </DesignTime>
  </ViewAttribute>
  <ViewAttribute
    Name="WorkOrder"
    IsUpdateable="false"
    IsPersistent="false"
    PrecisionRule="true"
    Precision="7"
    Type="java.lang.String"
    ColumnType="VARCHAR2"
    AliasName="WORK_ORDER"
    Expression="WORK_ORDER"
    SQLType="VARCHAR">
    <DesignTime>
      <Attr Name="_DisplaySize" Value="7"/>
    </DesignTime>
  </ViewAttribute>
  <ViewAttribute
    Name="Comments"
    IsUpdateable="false"
    IsPersistent="false"
    PrecisionRule="true"
    Precision="50"
    Type="java.lang.String"
    ColumnType="VARCHAR2"
    AliasName="COMMENTS"
    Expression="COMMENTS"
    SQLType="VARCHAR">
    <DesignTime>
      <Attr Name="_DisplaySize" Value="50"/>
    </DesignTime>
  </ViewAttribute>
  <ViewAttribute
    Name="CreatedDt"
    IsUpdateable="false"
    IsPersistent="false"
    PrecisionRule="true"
    Type="oracle.jbo.domain.Date"
    ColumnType="DATE"
    AliasName="CREATED_DT"
    Expression="CREATED_DT"
    SQLType="DATE">
    <DesignTime>
      <Attr Name="_DisplaySize" Value="7"/>
    </DesignTime>
  </ViewAttribute>
  <ViewAttribute
    Name="LastUpdDt"
    IsUpdateable="false"
    IsPersistent="false"
    PrecisionRule="true"
    Type="oracle.jbo.domain.Date"
    ColumnType="DATE"
    AliasName="LAST_UPD_DT"
    Expression="LAST_UPD_DT"
    SQLType="DATE">
    <DesignTime>
      <Attr Name="_DisplaySize" Value="7"/>
    </DesignTime>
  </ViewAttribute>
  <ViewAttribute
    Name="LastUpdUser"
    IsUpdateable="false"
    IsPersistent="false"
    PrecisionRule="true"
    Precision="30"
    Type="java.lang.String"
    ColumnType="VARCHAR2"
    AliasName="LAST_UPD_USER"
    Expression="LAST_UPD_USER"
    SQLType="VARCHAR">
    <DesignTime>
      <Attr Name="_DisplaySize" Value="30"/>
    </DesignTime>
  </ViewAttribute>
  <ViewAttribute
    Name="LastUpdPgm"
    IsUpdateable="false"
    IsPersistent="false"
    PrecisionRule="true"
    Precision="30"
    Type="java.lang.String"
    ColumnType="VARCHAR2"
    AliasName="LAST_UPD_PGM"
    Expression="LAST_UPD_PGM"
    SQLType="VARCHAR">
    <DesignTime>
      <Attr Name="_DisplaySize" Value="30"/>
    </DesignTime>
  </ViewAttribute>
  <AttrArray Name="KeyAttributes">
    <Item Value="ParkingSpaceId"/>
  </AttrArray>
</ViewObject>
